qphGamma/__init__.py
qphGamma/constants.py
qphGamma/daligault_energy_avg_gamma.py
qphGamma/daligault_gamma.py
qphGamma/fermi_gas_dos.py
qphGamma/fermi_gas_params.py
qphGamma/fermi_liquid_energy_avg_gamma.py
qphGamma/fermi_liquid_gamma.py
qphGamma/gw_energy_avg_gamma.py
qphGamma/gw_gamma.py
qphGamma/vasp_dos.py
qphGamma/vasp_param.py
qphGamma/vignale_gamma.py
qphGamma-0.2.2.dist-info/LICENSE.txt
qphGamma-0.2.2.dist-info/METADATA
qphGamma-0.2.2.dist-info/WHEEL
qphGamma-0.2.2.dist-info/top_level.txt
qphGamma-0.2.2.dist-info/RECORD
