Metadata-Version: 2.1
Name: qphGamma
Version: 0.2.2
Summary: A package for finding quasiparticle and quasihole scattering rates
Home-page: https://github.com/brobinson10296/qphGamma
Download-URL: https://github.com/brobinson10296/qphGamma/archive/main.zip
Author: Brian Robinson
Author-email: b.p.robinson102@gmail.com
Keywords: first principles,VASP,Fermi gas,Fermi liquid,e-e scattering
License-File: LICENSE.txt
Requires-Dist: numpy
Requires-Dist: pandas
Requires-Dist: scipy
Requires-Dist: py4vasp
Requires-Dist: plasmapy
